sourcemeta_jsonschema/__init__.py
sourcemeta_jsonschema/__main__.py
sourcemeta_jsonschema/jsonschema-darwin-arm64
sourcemeta_jsonschema/jsonschema-darwin-x86_64
sourcemeta_jsonschema/jsonschema-linux-arm64
sourcemeta_jsonschema/jsonschema-linux-x86_64
sourcemeta_jsonschema/jsonschema-windows-x86_64.exe
sourcemeta_jsonschema-14.0.4.dist-info/METADATA
sourcemeta_jsonschema-14.0.4.dist-info/WHEEL
sourcemeta_jsonschema-14.0.4.dist-info/entry_points.txt
sourcemeta_jsonschema-14.0.4.dist-info/top_level.txt
sourcemeta_jsonschema-14.0.4.dist-info/RECORD
